minesweeper/__init__.py
minesweeper/commands.py
minesweeper/game.py
minesweeper/main.py
minesweeper/models.py
minesweeper/renderer.py
minesweeper_cli-1.0.3.dist-info/licenses/LICENSE
minesweeper_cli-1.0.3.dist-info/METADATA
minesweeper_cli-1.0.3.dist-info/WHEEL
minesweeper_cli-1.0.3.dist-info/entry_points.txt
minesweeper_cli-1.0.3.dist-info/top_level.txt
minesweeper_cli-1.0.3.dist-info/RECORD
