Metadata-Version: 2.4
Name: minesweeper-cli
Version: 1.0.3
Summary: Classic Minesweeper game for the terminal with colorful CLI interface
Author-email: "Javier Novoa C." <jstitch@gmail.com>
License: GPL-3.0
Project-URL: Homepage, https://gitlab.com/jstitch/minesweeper-cli
Project-URL: Repository, https://gitlab.com/jstitch/minesweeper-cli
Keywords: minesweeper,game,cli,terminal,puzzle
Classifier: Development Status :: 5 - Production/Stable
Classifier: Environment :: Console
Classifier: Intended Audience :: End Users/Desktop
Classifier: License :: OSI Approved :: GNU General Public License v2 (GPLv2)
Classifier: Operating System :: OS Independent
Classifier: Programming Language :: Python :: 3
Classifier: Programming Language :: Python :: 3.9
Classifier: Programming Language :: Python :: 3.10
Classifier: Programming Language :: Python :: 3.11
Classifier: Programming Language :: Python :: 3.12
Classifier: Topic :: Games/Entertainment :: Puzzle Games
Requires-Python: >=3.9
License-File: LICENSE
Requires-Dist: click>=8.0
Requires-Dist: colorama>=0.4
Requires-Dist: ruff>=0.13.0
Provides-Extra: dev
Requires-Dist: black>=22.0; extra == "dev"
Requires-Dist: ruff>=0.13.0; extra == "dev"
Dynamic: license-file
